[{"BundleID":"com.go5go5.herogam.coin6yuan","SpriteName":"cz_goumai_6","Des":"6 \u5757 60","Reward":60},{"BundleID":"com.go5go5.herogam.coin18yuan","SpriteName":"cz_goumai_18","Des":"18\u5757100","Reward":100},{"BundleID":"com.go5go5.herogam.coin30yuan","SpriteName":"cz_goumai_30","Des":"30\u5757300","Reward":300},{"BundleID":"com.go5go5.herogam.coin60yuan","SpriteName":"cz_goumai_60","Des":"60\u5757600","Reward":600},{"BundleID":"com.go5go5.herogam.coin98yuan","SpriteName":"cz_goumai_98","Des":"98\u5757980","Reward":980}]